<?xml version="1.0" encoding="UTF-8" ?>

<!DOCTYPE sqlMap      
    PUBLIC "-//ibatis.apache.org//DTD SQL Map 2.0//EN"      
    "http://ibatis.apache.org/dtd/sql-map-2.dtd">

<sqlMap namespace="Permissions">

    <!-- Use type aliases to avoid typing the full classname every time. -->
    <typeAlias alias="Permissions" type="fi.mml.portti.domain.permissions.Permissions" />
    <typeAlias alias="Resource" type="fi.nls.oskari.permission.domain.Resource" />
    <typeAlias alias="Permission" type="fi.nls.oskari.permission.domain.Permission" />


    <resultMap id="permissionsResult" class="HashMap">
        <result property="id" column="id" />
        <result property="resourceMapping" column="resource_mapping" />
        <result property="resourceType" column="resource_type" />
        <result property="externalId" column="externalId" />
        <result property="externalIdType" column="externalType" />
        <result property="permissions" column="permission" />
    </resultMap>

    <!-- vanhentunut -->
    <parameterMap id="resourceUserIdAndPermissionsTypeParam" class="Map">
        <parameter property="resourceUserId" />
        <parameter property="permissionsType" />
    </parameterMap>

    <parameterMap id="permissionsOfResourceParam" class="Map">
        <parameter property="resourceName" />
        <parameter property="resourceNamespace" />
        <parameter property="resourceType" />
        <parameter property="externalIdType"/>
    </parameterMap>
    
    <parameterMap id="deletePermissionsParam" class="Map">
        <parameter property="resourceName" />
        <parameter property="resourceNamespace" />
        <parameter property="resourceType" />
        <parameter property="externalId" />
        <parameter property="externalIdType" />
        <parameter property="permissionsType"/>
    </parameterMap>

    <!-- vanhentunut -->
    <parameterMap id="resourceUserParam" class="Map">
        <parameter property="resourceName" />
        <parameter property="resourceNamespace" />
        <parameter property="resourceType" />
        <parameter property="externalId" />
        <parameter property="externalIdType" />
    </parameterMap>

    <parameterMap id="resourceParam" class="Map">
        <parameter property="resourceType" />
        <parameter property="resourceMapping" />
    </parameterMap>

   
    <parameterMap id="externalIdsAndLayerId" class="Map">
        <parameter property="idList" />
        <parameter property="id" />
    </parameterMap>
    
    <parameterMap id="externalIds" class="Map">
        <parameter property="idList" />
    </parameterMap>
   
    
    <resultMap id="publishPermissionsList" class="HashMap">
        <result property="resourceMapping" />
        <result property="externalId" />
    </resultMap>
    
   
    
    
    <parameterMap id="publishPermissionsList3" class="HashMap">
        <parameter property="resourceType" />
    </parameterMap>

    <parameterMap id="mapping_id" class="HashMap">
        <parameter property="resourceMapping" />
        <parameter property="externalId" />
    </parameterMap>
    
    <select id="maxId" resultClass="int">
        select max(id) from oskari_resource
    </select>


<!-- uudet mappaukset -->
    <parameterMap id="resourceMap" class="HashMap">
        <parameter property="resourceMapping" />
        <parameter property="resourceType" />
    </parameterMap>

    <parameterMap id="permissionMap" class="HashMap">
        <parameter property="oskariResourceId" />
        <parameter property="externalType" />
        <parameter property="permission" />
        <parameter property="externalId" />
    </parameterMap>

    <parameterMap id="layerPermissionResourceParams" class="Map">
        <parameter property="resourceMapping" />
        <parameter property="externalId" />
        <parameter property="externalType" />
        <parameter property="permission" />
    </parameterMap>

    <resultMap id="permission" class="Permission">
        <result property="id" column="perm_id" />
        <result property="type" column="permission" />
        <result property="externalType" column="perm_ext_type" />
        <result property="externalId" column="perm_ext_id" />
    </resultMap>

    <resultMap id="resource" class="Resource" groupBy="id">
        <result property="id" column="res_id" />
        <result property="mapping" column="res_mapping" />
        <result property="type" column="res_type" />
        <result property="permissions" resultMap="Permissions.permission" javaType="java.util.ArrayList" />
    </resultMap>

    <select id="findResourceWithMapping"  resultMap="resource" parameterClass="java.util.HashMap">
        SELECT
            p.id as perm_id, r.id as res_id,
            r.resource_type as res_type, r.resource_mapping as res_mapping,
            p.external_type as perm_ext_type, p.external_id as perm_ext_id, p.permission as permission
        FROM
            oskari_resource r
        LEFT JOIN
            oskari_permission p ON r.id=p.oskari_resource_id
        WHERE
            r.resource_type = #type# AND
            r.resource_mapping = #mapping#;
    </select>

    <select id="findResourceById"  resultMap="resource" parameterClass="Long">
        SELECT
            p.id as perm_id, r.id as res_id,
            r.resource_type as res_type, r.resource_mapping as res_mapping,
            p.external_type as perm_ext_type, p.external_id as perm_ext_id, p.permission as permission
        FROM
            oskari_resource r
        LEFT JOIN
            oskari_permission p ON r.id=p.oskari_resource_id
        WHERE
            r.id != -1 AND
            r.id = #id#;
    </select>

    <select id="findPublishPermissions"  resultMap="publishPermissionsList" parameterClass="java.util.HashMap">
       select 
       	r.resource_mapping as resourceMapping,
       	p.external_id as externalId
       from 
       	oskari_resource r, oskari_permission p
 	   where r.id=p.oskari_resource_id
 	   	and p.permission = 'PUBLISH'
 	   	and p.external_type = 'ROLE'
        and r.resource_type=#resourceType#
    </select>

    <select id="findDownloadPermissions"  resultMap="publishPermissionsList" parameterClass="java.util.HashMap">
        select
        r.resource_mapping as resourceMapping,
        p.external_id as externalId
        from
        oskari_resource r, oskari_permission p
        where r.id=p.oskari_resource_id
        and p.permission = 'DOWNLOAD'
        and p.external_type = 'ROLE'
        and r.resource_type=#resourceType#
    </select>



    <select id="findEditPermissions"  resultMap="publishPermissionsList">
        select
        r.resource_mapping as resourceMapping,
        p.external_id as externalId
        from
        oskari_resource r, oskari_permission p
        where r.id=p.oskari_resource_id
        and p.permission = 'EDIT_LAYER_CONTENT'
        and p.external_type = 'ROLE'
    </select>

    
    
    <!-- fixed -->
    <select id="findResource" resultClass="int" parameterMap="resourceParam">
        select id
        from oskari_resource
        where resource_type=?
        and resource_mapping=?
        limit 1
    </select>


    <select id="findPermission" resultClass="int" parameterMap="permissionMap">
        select
            id
        from
            oskari_permission
        where
            oskari_resource_id = ?
            and external_type = ?
            and permission = ?
            and external_id = ?
        limit 1
    </select>

    <select id="findResourcesWithGrantedPermissions" resultClass="String" parameterClass="java.util.HashMap">

        select distinct
            r.resource_mapping
        from
            oskari_resource r, oskari_permission p
        where
            r.id=p.oskari_resource_id
            and r.resource_type=#resourceType#
            and p.external_type=#externalType#
            and p.permission=#permission#
            and p.external_id IN
        <iterate open="(" close=")" conjunction="," property="externalId" >
            #externalId[]#
        </iterate>
    </select>

    <!--  fixed -->
    <select id="findPermissionsOfResource" resultMap="permissionsResult" parameterClass="java.util.HashMap">
        select r.id as id, r.resource_mapping  as resource_mapping,
        r.resource_type as resource_type, p.external_id as externalId, p.external_type as externalType,
        p.permission as permission
        from oskari_resource r, oskari_permission p
        where r.id=p.oskari_resource_id
        and r.resource_mapping=#resourceMapping#
        and r.resource_type=#resourceType#
        and p.external_type=#externalIdType#
    </select>
    <!-- check -->
    <select id="findPermissionsOfResourceUser" resultMap="permissionsResult" parameterMap="resourceUserParam">
        select r.id as id, r.resource_mapping  as resource_mapping,
        r.resource_type as resource_type, p.external_id as externalId, p.external_type as externalType,
        p.permission as permission
        from oskari_resource r, oskari_permission p
        where r.id=p.oskari_resource_id
        and r.resource_mapping=?
        and r.resource_type=?
        and p.external_id=?
        and p.external_type=?
    </select>
    
    <parameterMap id="layerPermissionParams" class="Map">
        <parameter property="permissionType" /> <!--  javaType="java.lang.String" -->
        <parameter property="idList" /> <!--  javaType="java.util.List" -->
    </parameterMap>

    <!-- fixed -->
    <resultMap id="layerPermissionsResult" class="HashMap">
        <result property="layerId" column="layerId" />
        <result property="externalId" column="externalId" />
        <result property="externalType" column="externalType" />
        <result property="permission" column="permission" />
    </resultMap>

    <!-- fixed -->
    <select id="findPermissionsForLayerIdList" resultMap="layerPermissionsResult" parameterMap="layerPermissionParams">
        SELECT
            l.id as layerId,
            p.external_id as externalId,
            p.external_type as externalType,
            p.permission
      FROM
            oskari_resource u,
            oskari_permission p,
            oskari_maplayer l
      WHERE
            u.id = p.oskari_resource_id AND
            u.resource_mapping = l.type || '+' || l.url || '+' || l.name
            <isNotEmpty property="permissionsType">AND p.permission = #permissionType#</isNotEmpty>
            <isNotEmpty property="idList" prepend="and">
                l.id in
                <iterate open="(" close=")" conjunction="," property="idList" >
                    #idList[]#
                </iterate>
            </isNotEmpty>
      ORDER BY 
            l.id;
    </select>

    <!-- fixed -->
    <select id="findPermissionsForBaseLayerIdList" resultMap="layerPermissionsResult" parameterMap="layerPermissionParams">
        SELECT 
            l.id as layerId, 
            p.external_id as externalId,
            p.external_type as externalType,
            p.permission
      FROM 
            oskari_resource u,
            oskari_permission p,
            portti_layerclass l 
      WHERE
            u.id = p.oskari_resource_id AND
            u.resource_mapping = 'BASE+' || CAST(l.id AS character varying)
            <isNotEmpty property="permissionType">AND p.permission = #permissionType#</isNotEmpty>
            <isNotEmpty property="idList" prepend="and">
                l.id in
                <iterate open="(" close=")" conjunction="," property="idList" >
                    #idList[]#
                </iterate>
            </isNotEmpty>
      ORDER BY
            l.id;
    </select>

    <!--   vanhentunut -->
    <statement id="insert" parameterClass="Permissions" resultClass="int">
        insert into portti_resource_user (resource_name, resource_namespace, resource_type, externalid, externalid_type)
        values (#uniqueResourceName.name#, #uniqueResourceName.namespace#, #uniqueResourceName.type#, #externalId#, #externalIdType#)
    </statement>

    <!-- uusi -->
    <statement id="insertResource" parameterMap="resourceMap" resultClass="int">
        insert into oskari_resource (resource_mapping, resource_type)
        values (?, ?)
    </statement>

    <statement id="createResource" parameterClass="HashMap" resultClass="int">
        insert into oskari_resource (resource_mapping, resource_type)
        values (#mapping#, #type#) RETURNING id;
    </statement>

    <!-- uusi -->
    <statement id="insertPermission" parameterMap="permissionMap">
        insert into oskari_permission (oskari_resource_id, external_type, permission, external_id) values (?, ?, ?, ?)
    </statement>

    <!-- uusi -->
    <statement id="findOskariPermissionId"  parameterMap="layerPermissionResourceParams" resultClass="long">
        SELECT
            p.id
        FROM
            oskari_resource r,
            oskari_permission p
        WHERE
            r.id = p.oskari_resource_id AND
            r.resource_mapping = ? AND
            p.external_id = ? AND
            p.external_type = ? AND
            p.permission = ?
    </statement>

    <delete id="deleteResourcePermissions" parameterClass="long">
        delete from oskari_permission where oskari_resource_id = #id#
    </delete>

    <delete id="deleteResource" parameterClass="long">
        delete from oskari_resource where id = #id#
    </delete>

    <delete id="deletePermission" parameterClass="long">
        delete from oskari_permission where id = #id#
    </delete>

    <!-- fixed -->
    <select id="findMaplayerIdsForViewPermissionsByExternalIds" resultClass="HashMap" parameterMap="externalIds">
	    SELECT DISTINCT
		    map.id
		FROM
            oskari_resource osr,
            oskari_permission op,
            oskari_maplayer map
		WHERE
            op.permission = 'VIEW_LAYER' AND
            osr.id = op.oskari_resource_id AND
            osr.resource_type = 'maplayer' AND
            osr.resource_mapping = map.type || '+' || map.url || '+' || map.name AND
            op.external_Id IN
		    <iterate open="(" close=")" conjunction="," property="idList" >
                    #idList[]#
            </iterate>
		    
		    
    </select>

    <!-- fixed -->
    <select id="findMaplayerIdsForViewPublishedPermissionsByExternalIds" resultClass="HashMap" parameterMap="externalIds">
        SELECT DISTINCT
        map.id
        FROM
        oskari_resource osr,
        oskari_permission op,
        oskari_maplayer map
        WHERE
        (op.permission = 'VIEW_LAYER' OR op.permission = 'VIEW_PUBLISHED') AND
        osr.id = op.oskari_resource_id AND
        osr.resource_type = 'maplayer' AND
        osr.resource_mapping = map.type || '+' || map.url || '+' || map.name AND
        op.external_Id IN
        <iterate open="(" close=")" conjunction="," property="idList" >
            #idList[]#
        </iterate>
    </select>

    <!-- fixed -->
    <select id="hasViewPermissionForLayerByLayerId" resultClass="long" parameterMap="externalIdsAndLayerId">
        SELECT DISTINCT
            map.id
        FROM 
            oskari_resource osr,
            oskari_permission op,
            oskari_maplayer map
        WHERE
            op.permission = 'VIEW_LAYER' AND
            osr.id = op.oskari_resource_id AND
            osr.resource_type = 'maplayer' AND
            osr.resource_mapping = map.type || '+' || map.url || '+' || map.name AND
            op.external_Id IN
            <iterate open="(" close=")" conjunction="," property="idList" >
                    #idList[]#
            </iterate> AND
            map.id = #id#
    </select>


    <!-- fixed -->
    <select id="hasEditPermissionForLayerByLayerId" resultClass="long" parameterMap="externalIdsAndLayerId">
        SELECT DISTINCT
        map.id
        FROM
        oskari_resource ore,
        oskari_permission op,
        oskari_maplayer map
        WHERE
        op.permission = 'EDIT_LAYER_CONTENT' AND
        ore.id = op.oskari_resource_id AND
        ore.resource_type = 'maplayer' AND
        ore.resource_mapping = map.type || '+' || map.url || '+' || map.name AND
        op.external_Id IN
        <iterate open="(" close=")" conjunction="," property="idList" >
            #idList[]#
        </iterate> AND
        map.id = #id#
    </select>


    <select id="hasExecutePermission" parameterMap="mapping_id">
    SELECT
        r.resource_mapping
    FROM
        oskari_resource r,
        oskari_permission p
    WHERE
        r.id = p.oskari_resource_id AND
        r.resource_mapping = 'generic-functionality' AND
        p.external_id IN
        <iterate open="(" close=")" conjunction="," property="idList" >
            #idList[]#
        </iterate> AND
        p.external_type = 'ROLE' AND
        p.permission = 'ADD_MAPLAYER'
    </select>
    
    
</sqlMap>